pyctest
