Metadata-Version: 2.1
Name: pyctest
Version: 0.0.7rc0
Summary: Python wrappers for generating CTest and submitting to CDash without a CMake build system
Home-page: https://github.com/jrmadsen/pyctest.git
Author: Jonathan R. Madsen
Author-email: jonrobm.programming@gmail.com
Maintainer: Jonathan R. Madsen
Maintainer-email: jonrobm.programming@gmail.com
License: MIT
Keywords: cmake,ctest,pybind11
Platform: UNKNOWN
Classifier: Development Status :: 4 - Beta
Classifier: Intended Audience :: Developers
Classifier: Topic :: Utilities
Classifier: Natural Language :: English
Classifier: License :: OSI Approved :: MIT License
Classifier: Programming Language :: Python :: 2
Classifier: Programming Language :: Python :: 2.7
Classifier: Programming Language :: Python :: 3
Classifier: Programming Language :: Python :: 3.5
Classifier: Programming Language :: Python :: 3.6
Classifier: Programming Language :: Python :: Implementation :: CPython
Requires-Python: >=2.6
